Hector9000/HectorController.py
Hector9000/HectorHardware.py
Hector9000/HectorRemote.py
Hector9000/HectorServer.py
Hector9000/HectorSimulator.py
Hector9000/LEDStripServer.py
Hector9000/__init__.py
Hector9000/conf/HectorConfig.py
Hector9000/conf/__init__.py
Hector9000/conf/database.py
Hector9000/conf/drinks.py
Hector9000/conf/drinks_more_recipes.py
Hector9000/conf/hx711.py
Hector9000/tools/Editingredients.py
Hector9000/tools/SetValveIng.py
Hector9000/tools/__init__.py
Hector9000/tools/adjustValves.py
Hector9000/tools/clean.py
Hector9000/tools/valveclose.py
Hector9000/tools/valveopen.py
Hector9000/utils/HectorAPI.py
Hector9000/utils/LEDStripAPI.py
Hector9000/utils/LEDStripConnector.py
Hector9000/utils/Simple_LED_Connector.py
Hector9000/utils/__init__.py
tests/__init__.py
tests/test_HectorController.py
tests/test_HectorSimulator.py
tests/test_database.py
tests/helpers/__init__.py
tests/helpers/h9kTestHelper.py
Hector9000-0.1.0rc2.dist-info/LICENSE
Hector9000-0.1.0rc2.dist-info/METADATA
Hector9000-0.1.0rc2.dist-info/WHEEL
Hector9000-0.1.0rc2.dist-info/entry_points.txt
Hector9000-0.1.0rc2.dist-info/top_level.txt
Hector9000-0.1.0rc2.dist-info/RECORD
