Metadata-Version: 2.1
Name: Hector9000
Version: 0.1.0rc2
Summary: Fancy barbot with lots of needless features and ...of course... WiFi and a bunch of blinky LEDs
Home-page: https://github.com/H3c702/Hector9000
Author: DevTown
Author-email: Hector@dev-town.de
License: UNKNOWN
Platform: UNKNOWN
Classifier: Programming Language :: Python :: 3
Classifier: License :: OSI Approved :: MIT License
Classifier: Natural Language :: English
Classifier: Natural Language :: German
Classifier: Operating System :: OS Independent
Requires-Python: >=3.6
License-File: LICENSE
Requires-Dist: Adafruit-GPIO (==1.0.3)
Requires-Dist: Adafruit-PCA9685 (==1.0.1)
Requires-Dist: Adafruit-PureIO (>=1.1.5)
Requires-Dist: atomicwrites (==1.3.0)
Requires-Dist: adafruit-circuitpython-neopixel (==6.0.0)
Requires-Dist: attrs (==19.1.0)
Requires-Dist: board (==0.0.0.post0)
Requires-Dist: certifi (==2018.11.29)
Requires-Dist: chardet (==3.0.4)
Requires-Dist: docutils (==0.14)
Requires-Dist: idna (==2.8)
Requires-Dist: more-itertools (==7.0.0)
Requires-Dist: packaging (==19.0)
Requires-Dist: paho-mqtt (==1.6.1)
Requires-Dist: pluggy (==0.12.0)
Requires-Dist: py (==1.10.0)
Requires-Dist: Pygments (==2.7.4)
Requires-Dist: pyparsing (==2.4.0)
Requires-Dist: requests (==2.27.1)
Requires-Dist: six (==1.12.0)
Requires-Dist: urllib3 (==1.26.5)
Requires-Dist: wcwidth (==0.1.7)
Requires-Dist: webcolors (==1.3)
Requires-Dist: zipp (==3.1.0)
Provides-Extra: dev
Requires-Dist: pytest ; extra == 'dev'
Requires-Dist: flake8 ; extra == 'dev'
Requires-Dist: autopep8 ; extra == 'dev'
Provides-Extra: pi
Requires-Dist: RPi.GPIO (==0.7.0) ; extra == 'pi'
Requires-Dist: spidev (==3.5) ; extra == 'pi'
